clip_files.py
clip_files-0.4.1.dist-info/licenses/LICENSE
clip_files-0.4.1.dist-info/METADATA
clip_files-0.4.1.dist-info/WHEEL
clip_files-0.4.1.dist-info/entry_points.txt
clip_files-0.4.1.dist-info/top_level.txt
clip_files-0.4.1.dist-info/RECORD
