Metadata-Version: 2.4
Name: clip-files
Version: 0.4.1
Summary: clip-files copies.
Author-email: Bas Nijholt <bas@nijho.lt>
Project-URL: Homepage, https://github.com/basnijholt/clip-files
Requires-Python: >=3.8
License-File: LICENSE
Requires-Dist: pyperclip
Requires-Dist: tiktoken
Provides-Extra: test
Requires-Dist: pytest; extra == "test"
Requires-Dist: pre-commit; extra == "test"
Requires-Dist: coverage; extra == "test"
Requires-Dist: pytest-cov; extra == "test"
Provides-Extra: docs
Dynamic: license-file
